mt5b3/__init__.py
mt5b3/ai_utils.py
mt5b3/backtest.py
mt5b3/broker.py
mt5b3/finmath.py
mt5b3/mt5b3.py
mt5b3/operations.py
mt5b3/sampleTraders.py
mt5b3/tech.py
mt5b3-0.0.2.dist-info/LICENSE.txt
mt5b3-0.0.2.dist-info/METADATA
mt5b3-0.0.2.dist-info/WHEEL
mt5b3-0.0.2.dist-info/top_level.txt
mt5b3-0.0.2.dist-info/RECORD
