Metadata-Version: 2.1
Name: mt5b3
Version: 0.0.2
Summary: mt5b3 provides access to the B3 stock exchange to python programs through Metatrader and some Brazilian brokers
Home-page: https://github.com/paulo-al-castro/mt5b3/
Author: Paulo Andre Castro
Author-email: paulo.al.castro@gmail.com
License: UNKNOWN
Platform: UNKNOWN
Classifier: Programming Language :: Python :: 3
Classifier: License :: OSI Approved :: MIT License
Classifier: Operating System :: OS Independent
